dwhois
setup.py
bin/dwhois
bin/dwhois-user
bin/dwhois-worker
dwhois/__init__.py
dwhois/cache.py
dwhois/config.py
dwhois/query.py
dwhois/timing.py
dwhois/whois.py
dwhois/worker.py
dwhois.egg-info/PKG-INFO
dwhois.egg-info/SOURCES.txt
dwhois.egg-info/dependency_links.txt
dwhois.egg-info/requires.txt
dwhois.egg-info/top_level.txt
dwhois/tests/__init__.py
dwhois/tests/timing.py