Metadata-Version: 1.1
Name: dwhois
Version: 0.11
Summary: Distributed WHOIS
Home-page: https://github.com/hstern/dwhois
Author: Henry Stern
Author-email: henry@stern.ca
License: LGPL v3
Platform: UNKNOWN
Classifier: Development Status :: 3 - Alpha
Classifier: Environment :: No Input/Output (Daemon)
Classifier: Intended Audience :: System Administrators
Classifier: License :: OSI Approved :: GNU Lesser General Public License v3 (LGPLv3)
Classifier: Operating System :: POSIX :: Linux
Classifier: Topic :: Internet
Classifier: Topic :: Security
Classifier: Topic :: System :: Networking
